Workbook
Name Days_PM: Inputs!$B$25
Name FX_AI: Inputs!$B$23
Name Markup: Inputs!$B$22

Sheet README
A1: SaaS AI Cost-of-Tenant Calculator
A3: Purpose | B3: Per-tenant AI cost engine for SaaS with LLM-backed features. Models token cost (input + output × model price), eval overhead, retraining amortisation, vector-store cost, RAG retrieval, and observability — across Free / Pro / Enterprise tiers. Produces AI gross margin per tier, % of customers above the cost ceiling, and a stress-test waterfall for token-inflation and usage-shock scenarios.
A5: Sheets in this workbook
A6: Inputs | B6: Tenants by tier, users/tenant, prompts/day, tokens, model selection, fixed costs, markup, FX.
A7: Cost-Per-Tenant | B7: Monthly per-tenant cost formula by tier.
A8: Margin-Analysis | B8: Tier price vs AI cost → AI GM per tier, contribution margin with S&M attribution.
A9: Sensitivity | B9: 2-D tables: tokens-per-prompt × $/1k input; prompts/day × users/tenant.
A10: Stress-Test | B10: Waterfall: +50/+100/+200% tokens; 2× usage; retraining 2×; eval 2×; model deprecation.
A11: Dashboard | B11: Cost per tier; AI GM per tier; % customers above cost ceiling; charts.
A12: Africa-Notes | B12: USD AI pricing, FX hedging, local-LLM fallback, usage caps.
A14: Owner | B14: Head of AI / CFO joint ownership
A15: Update cadence | B15: Monthly when LLM provider pricing changes; quarterly for usage assumptions; before each pricing/packaging change.
A16: Living-plan discipline | B16: All yellow cells are user-editable inputs. White cells are formulas — do not overwrite. Refresh inputs on the cadence above. Any variance >10% versus plan triggers a re-plan loop per skills/meta-living-plan-governance.
A17: Sources / methodology | B17: ai-economics-framework.md (this engine); OpenAI/Anthropic/Together public pricing; tracker.ai_economics; Cotton (Run a SaaS Business) Rule of 3-and-10 cost-margin discipline.
A19: Currency convention | B19: All inputs in USD. Use FX cell on Inputs sheet to display local-currency equivalents (UGX, KES, NGN, ZAR, EGP). Mobile-money (M-Pesa / MoMo) and card-rail fees enter as % of revenue.

Sheet Inputs
A1: Inputs — AI Cost-of-Tenant
A2: Yellow = input. White = formula. Three tiers: Free, Pro, Enterprise.
A4: 1. Tenant Mix
B5: Free | C5: Pro | D5: Enterprise | F5: Notes
A6: Tenants (count) | B6: 500 | C6: 200 | D6: 50 | F6: Active customer count by tier.
A7: Users per tenant | B7: 3 | C7: 8 | D7: 25 | F7: Number of seats per tenant.
A8: Prompts per user per day | B8: 5 | C8: 15 | D8: 30 | F8: Daily AI prompt volume per active user.
A9: Input tokens per prompt | B9: 400 | C9: 800 | D9: 2000 | F9: Avg input length (prompt + RAG context + chat history).
A10: Output tokens per prompt | B10: 200 | C10: 500 | D10: 1200 | F10: Avg generation length.
A11: $ per 1k input tokens | B11: 0.0001 | C11: 0.00015 | D11: 0.0025 | F11: Free=Llama-class; Pro=GPT-4o-mini-class; Ent=GPT-4o/Claude-Sonnet-class.
A12: $ per 1k output tokens | B12: 0.0002 | C12: 0.0006 | D12: 0.01 | F12: Output-tier USD pricing.
A13: Eval / guardrails overhead % | B13: 0.1 | C13: 0.1 | D13: 0.15 | F13: % of token cost spent on evals (re-runs, judge models).
A14: Retraining $/month per tenant | B14: 0 | C14: 1 | D14: 8 | F14: Amortised fine-tune / embed-refresh cost.
A15: Vector store $/month per tenant | B15: 0 | C15: 2 | D15: 15 | F15: Pinecone / Qdrant / Weaviate / pgvector.
A16: RAG retrieval $/query | B16: 0 | C16: 0.0001 | D16: 0.0003 | F16: Vector search + reranker pass.
A17: Observability $/call | B17: 0 | C17: 5e-05 | D17: 0.0002 | F17: Langfuse / Helicone / Phoenix logging.
... A20: Other COGS % of price | B20: 0 | C20: 0.2 | D20: 0.15 | F20: Non-AI COGS (hosting, support, rails).
A21: 2. Pricing Markup & FX
A22: Internal markup (cost-ceiling tolerance % of price) | B22: 0.3 | F22: If AI cost > markup × price, flag tenant as above ceiling.
A23: FX rate (local per USD) | B23: 3800
A24: Reporting currency | B24: UGX
A25: Days per month for prompt count | B25: 22 | F25: Working days; reduce for B2C consumer or weekend-heavy workloads.

Sheet Cost-Per-Tenant
A1: Cost Per Tenant (USD / month)
A2: Formula breakdown by tier — every component pulled from Inputs.
A3: Component | B3: Free | C3: Pro | D3: Enterprise | F3: Formula
A4: Token cost (input) | B4: =(Inputs!B7*Inputs!B8*Days_PM*Inputs!B9*Inputs!B11)/1000 -> 0 | C4: =(Inputs!C7*Inputs!C8*Days_PM*Inputs!C9*Inputs!C11)/1000 -> 0 | D4: =(Inputs!D7*Inputs!D8*Days_PM*Inputs!D9*Inputs!D11)/1000 -> 0 | F4: Tier formula derived from Inputs row × users × prompts × Days_PM, plus fixed-cost rows.
A5: Token cost (output) | B5: =(Inputs!B7*Inputs!B8*Days_PM*Inputs!B10*Inputs!B12)/1000 -> 0 | C5: =(Inputs!C7*Inputs!C8*Days_PM*Inputs!C10*Inputs!C12)/1000 -> 0 | D5: =(Inputs!D7*Inputs!D8*Days_PM*Inputs!D10*Inputs!D12)/1000 -> 0 | F5: Tier formula derived from Inputs row × users × prompts × Days_PM, plus fixed-cost rows.
A6: Eval / guardrails | B6: =(Inputs!B7*Inputs!B8*Days_PM*(Inputs!B9*Inputs!B11+Inputs!B10*Inputs!B12)/1000)*Inputs!B13 -> 0 | C6: =(Inputs!C7*Inputs!C8*Days_PM*(Inputs!C9*Inputs!C11+Inputs!C10*Inputs!C12)/1000)*Inputs!C13 -> 0 | D6: =(Inputs!D7*Inputs!D8*Days_PM*(Inputs!D9*Inputs!D11+Inputs!D10*Inputs!D12)/1000)*Inputs!D13 -> 0 | F6: Tier formula derived from Inputs row × users × prompts × Days_PM, plus fixed-cost rows.
A7: Retraining (amortised) | B7: =Inputs!B14 -> 0 | C7: =Inputs!C14 -> 0 | D7: =Inputs!D14 -> 0 | F7: Tier formula derived from Inputs row × users × prompts × Days_PM, plus fixed-cost rows.
A8: Vector store (fixed/tenant) | B8: =Inputs!B15 -> 0 | C8: =Inputs!C15 -> 0 | D8: =Inputs!D15 -> 0 | F8: Tier formula derived from Inputs row × users × prompts × Days_PM, plus fixed-cost rows.
A9: RAG retrieval | B9: =Inputs!B7*Inputs!B8*Days_PM*Inputs!B16 -> 0 | C9: =Inputs!C7*Inputs!C8*Days_PM*Inputs!C16 -> 0 | D9: =Inputs!D7*Inputs!D8*Days_PM*Inputs!D16 -> 0 | F9: Tier formula derived from Inputs row × users × prompts × Days_PM, plus fixed-cost rows.
A10: Observability | B10: =Inputs!B7*Inputs!B8*Days_PM*Inputs!B17 -> 0 | C10: =Inputs!C7*Inputs!C8*Days_PM*Inputs!C17 -> 0 | D10: =Inputs!D7*Inputs!D8*Days_PM*Inputs!D17 -> 0 | F10: Tier formula derived from Inputs row × users × prompts × Days_PM, plus fixed-cost rows.
A11: TOTAL AI cost per tenant / month | B11: =SUM(B4:B10) -> 0 | C11: =SUM(C4:C10) -> 0 | D11: =SUM(D4:D10) -> 0
A12: × Tenants in tier | B12: =Inputs!B6 -> 0 | C12: =Inputs!C6 -> 0 | D12: =Inputs!D6 -> 0
A13: Total tier AI cost / month | B13: =B11*B12 -> 0 | C13: =C11*C12 -> 0 | D13: =D11*D12 -> 0
A14: Total AI cost / year | B14: =B13*12 -> 0 | C14: =C13*12 -> 0 | D14: =D13*12 -> 0
A15: GRAND TOTAL AI cost / year (all tiers) | B15: =SUM(B14:D14) -> 0

Sheet Margin-Analysis
A1: AI Margin Analysis — by Tier
A3: Line | B3: Free | C3: Pro | D3: Enterprise
A4: Tier price ($/month) | B4: =Inputs!B18 -> 0 | C4: =Inputs!C18 -> 0 | D4: =Inputs!D18 -> 0
A5: AI cost per tenant ($/month) | B5: ='Cost-Per-Tenant'!B11 -> 0 | C5: ='Cost-Per-Tenant'!C11 -> 0 | D5: ='Cost-Per-Tenant'!D11 -> 0
A6: AI GM $ | B6: =B4-B5 -> 0 | C6: =C4-C5 -> 0 | D6: =D4-D5 -> 0
A7: AI GM % | B7: =IF(B4>0,(B4-B5)/B4,-1) -> 0 | C7: =IF(C4>0,(C4-C5)/C4,-1) -> 0 | D7: =IF(D4>0,(D4-D5)/D4,-1) -> 0
A8: S&M attribution $ | B8: =Inputs!B18*Inputs!B19 -> 0 | C8: =Inputs!C18*Inputs!C19 -> 0 | D8: =Inputs!D18*Inputs!D19 -> 0
A9: Other COGS $ | B9: =Inputs!B18*Inputs!B20 -> 0 | C9: =Inputs!C18*Inputs!C20 -> 0 | D9: =Inputs!D18*Inputs!D20 -> 0
A10: Contribution margin $ | B10: =B4-B5-B7-B8 -> 0 | C10: =C4-C5-C7-C8 -> 0 | D10: =D4-D5-D7-D8 -> 0
A11: Contribution margin % | B11: =IF(B4>0,(B4-B5-B7-B8)/B4,-1) -> 0 | C11: =IF(C4>0,(C4-C5-C7-C8)/C4,-1) -> 0 | D11: =IF(D4>0,(D4-D5-D7-D8)/D4,-1) -> 0
A12: Cost ceiling $ (Markup × price) | B12: =Inputs!B18*Markup -> 0 | C12: =Inputs!C18*Markup -> 0 | D12: =Inputs!D18*Markup -> 0
A13: Above ceiling? (AI cost > ceiling) | B13: =IF(B5>B11,"YES","no") -> 0 | C13: =IF(C5>C11,"YES","no") -> 0 | D13: =IF(D5>D11,"YES","no") -> 0

Sheet Sensitivity
A1: Sensitivity — tokens-per-prompt × $/1k (Enterprise tier)
A3: Reading: Enterprise cost/tenant/mo @ varied tokens & price.
A5: Tokens/prompt ↓ $/1k → | B5: 0.001 | C5: 0.0025 | D5: 0.005 | E5: 0.0075 | F5: 0.01 | G5: 0.015 | H5: 0.02
A6: 500 | B6: =(Inputs!D7*Inputs!D8*Days_PM*500*0.001)/1000 -> 0 | C6: =(Inputs!D7*Inputs!D8*Days_PM*500*0.0025)/1000 -> 0 | D6: =(Inputs!D7*Inputs!D8*Days_PM*500*0.005)/1000 -> 0 | E6: =(Inputs!D7*Inputs!D8*Days_PM*500*0.0075)/1000 -> 0 | F6: =(Inputs!D7*Inputs!D8*Days_PM*500*0.01)/1000 -> 0 | G6: =(Inputs!D7*Inputs!D8*Days_PM*500*0.015)/1000 -> 0 | H6: =(Inputs!D7*Inputs!D8*Days_PM*500*0.02)/1000 -> 0
A7: 1000 | B7: =(Inputs!D7*Inputs!D8*Days_PM*1000*0.001)/1000 -> 0 | C7: =(Inputs!D7*Inputs!D8*Days_PM*1000*0.0025)/1000 -> 0 | D7: =(Inputs!D7*Inputs!D8*Days_PM*1000*0.005)/1000 -> 0 | E7: =(Inputs!D7*Inputs!D8*Days_PM*1000*0.0075)/1000 -> 0 | F7: =(Inputs!D7*Inputs!D8*Days_PM*1000*0.01)/1000 -> 0 | G7: =(Inputs!D7*Inputs!D8*Days_PM*1000*0.015)/1000 -> 0 | H7: =(Inputs!D7*Inputs!D8*Days_PM*1000*0.02)/1000 -> 0
A8: 1500 | B8: =(Inputs!D7*Inputs!D8*Days_PM*1500*0.001)/1000 -> 0 | C8: =(Inputs!D7*Inputs!D8*Days_PM*1500*0.0025)/1000 -> 0 | D8: =(Inputs!D7*Inputs!D8*Days_PM*1500*0.005)/1000 -> 0 | E8: =(Inputs!D7*Inputs!D8*Days_PM*1500*0.0075)/1000 -> 0 | F8: =(Inputs!D7*Inputs!D8*Days_PM*1500*0.01)/1000 -> 0 | G8: =(Inputs!D7*Inputs!D8*Days_PM*1500*0.015)/1000 -> 0 | H8: =(Inputs!D7*Inputs!D8*Days_PM*1500*0.02)/1000 -> 0
A9: 2000 | B9: =(Inputs!D7*Inputs!D8*Days_PM*2000*0.001)/1000 -> 0 | C9: =(Inputs!D7*Inputs!D8*Days_PM*2000*0.0025)/1000 -> 0 | D9: =(Inputs!D7*Inputs!D8*Days_PM*2000*0.005)/1000 -> 0 | E9: =(Inputs!D7*Inputs!D8*Days_PM*2000*0.0075)/1000 -> 0 | F9: =(Inputs!D7*Inputs!D8*Days_PM*2000*0.01)/1000 -> 0 | G9: =(Inputs!D7*Inputs!D8*Days_PM*2000*0.015)/1000 -> 0 | H9: =(Inputs!D7*Inputs!D8*Days_PM*2000*0.02)/1000 -> 0
A10: 3000 | B10: =(Inputs!D7*Inputs!D8*Days_PM*3000*0.001)/1000 -> 0 | C10: =(Inputs!D7*Inputs!D8*Days_PM*3000*0.0025)/1000 -> 0 | D10: =(Inputs!D7*Inputs!D8*Days_PM*3000*0.005)/1000 -> 0 | E10: =(Inputs!D7*Inputs!D8*Days_PM*3000*0.0075)/1000 -> 0 | F10: =(Inputs!D7*Inputs!D8*Days_PM*3000*0.01)/1000 -> 0 | G10: =(Inputs!D7*Inputs!D8*Days_PM*3000*0.015)/1000 -> 0 | H10: =(Inputs!D7*Inputs!D8*Days_PM*3000*0.02)/1000 -> 0
A11: 4000 | B11: =(Inputs!D7*Inputs!D8*Days_PM*4000*0.001)/1000 -> 0 | C11: =(Inputs!D7*Inputs!D8*Days_PM*4000*0.0025)/1000 -> 0 | D11: =(Inputs!D7*Inputs!D8*Days_PM*4000*0.005)/1000 -> 0 | E11: =(Inputs!D7*Inputs!D8*Days_PM*4000*0.0075)/1000 -> 0 | F11: =(Inputs!D7*Inputs!D8*Days_PM*4000*0.01)/1000 -> 0 | G11: =(Inputs!D7*Inputs!D8*Days_PM*4000*0.015)/1000 -> 0 | H11: =(Inputs!D7*Inputs!D8*Days_PM*4000*0.02)/1000 -> 0
A12: 6000 | B12: =(Inputs!D7*Inputs!D8*Days_PM*6000*0.001)/1000 -> 0 | C12: =(Inputs!D7*Inputs!D8*Days_PM*6000*0.0025)/1000 -> 0 | D12: =(Inputs!D7*Inputs!D8*Days_PM*6000*0.005)/1000 -> 0 | E12: =(Inputs!D7*Inputs!D8*Days_PM*6000*0.0075)/1000 -> 0 | F12: =(Inputs!D7*Inputs!D8*Days_PM*6000*0.01)/1000 -> 0 | G12: =(Inputs!D7*Inputs!D8*Days_PM*6000*0.015)/1000 -> 0 | H12: =(Inputs!D7*Inputs!D8*Days_PM*6000*0.02)/1000 -> 0
A15: Sensitivity — prompts/day × users/tenant (Pro tier, holding tokens fixed)
A17: Prompts/day ↓ Users/tenant → | B17: 2 | C17: 5 | D17: 8 | E17: 12 | F17: 20 | G17: 30 | H17: 50
A18: 5 | B18: =(2*5*Days_PM*(Inputs!C9*Inputs!C11+Inputs!C10*Inputs!C12))/1000 -> 0 | C18: =(5*5*Days_PM*(Inputs!C9*Inputs!C11+Inputs!C10*Inputs!C12))/1000 -> 0 | D18: =(8*5*Days_PM*(Inputs!C9*Inputs!C11+Inputs!C10*Inputs!C12))/1000 -> 0 | E18: =(12*5*Days_PM*(Inputs!C9*Inputs!C11+Inputs!C10*Inputs!C12))/1000 -> 0 | F18: =(20*5*Days_PM*(Inputs!C9*Inputs!C11+Inputs!C10*Inputs!C12))/1000 -> 0 | G18: =(30*5*Days_PM*(Inputs!C9*Inputs!C11+Inputs!C10*Inputs!C12))/1000 -> 0 | H18: =(50*5*Days_PM*(Inputs!C9*Inputs!C11+Inputs!C10*Inputs!C12))/1000 -> 0
A19: 10 | B19: =(2*10*Days_PM*(Inputs!C9*Inputs!C11+Inputs!C10*Inputs!C12))/1000 -> 0 | C19: =(5*10*Days_PM*(Inputs!C9*Inputs!C11+Inputs!C10*Inputs!C12))/1000 -> 0 | D19: =(8*10*Days_PM*(Inputs!C9*Inputs!C11+Inputs!C10*Inputs!C12))/1000 -> 0 | E19: =(12*10*Days_PM*(Inputs!C9*Inputs!C11+Inputs!C10*Inputs!C12))/1000 -> 0 | F19: =(20*10*Days_PM*(Inputs!C9*Inputs!C11+Inputs!C10*Inputs!C12))/1000 -> 0 | G19: =(30*10*Days_PM*(Inputs!C9*Inputs!C11+Inputs!C10*Inputs!C12))/1000 -> 0 | H19: =(50*10*Days_PM*(Inputs!C9*Inputs!C11+Inputs!C10*Inputs!C12))/1000 -> 0
A20: 15 | B20: =(2*15*Days_PM*(Inputs!C9*Inputs!C11+Inputs!C10*Inputs!C12))/1000 -> 0 | C20: =(5*15*Days_PM*(Inputs!C9*Inputs!C11+Inputs!C10*Inputs!C12))/1000 -> 0 | D20: =(8*15*Days_PM*(Inputs!C9*Inputs!C11+Inputs!C10*Inputs!C12))/1000 -> 0 | E20: =(12*15*Days_PM*(Inputs!C9*Inputs!C11+Inputs!C10*Inputs!C12))/1000 -> 0 | F20: =(20*15*Days_PM*(Inputs!C9*Inputs!C11+Inputs!C10*Inputs!C12))/1000 -> 0 | G20: =(30*15*Days_PM*(Inputs!C9*Inputs!C11+Inputs!C10*Inputs!C12))/1000 -> 0 | H20: =(50*15*Days_PM*(Inputs!C9*Inputs!C11+Inputs!C10*Inputs!C12))/1000 -> 0
A21: 20 | B21: =(2*20*Days_PM*(Inputs!C9*Inputs!C11+Inputs!C10*Inputs!C12))/1000 -> 0 | C21: =(5*20*Days_PM*(Inputs!C9*Inputs!C11+Inputs!C10*Inputs!C12))/1000 -> 0 | D21: =(8*20*Days_PM*(Inputs!C9*Inputs!C11+Inputs!C10*Inputs!C12))/1000 -> 0 | E21: =(12*20*Days_PM*(Inputs!C9*Inputs!C11+Inputs!C10*Inputs!C12))/1000 -> 0 | F21: =(20*20*Days_PM*(Inputs!C9*Inputs!C11+Inputs!C10*Inputs!C12))/1000 -> 0 | G21: =(30*20*Days_PM*(Inputs!C9*Inputs!C11+Inputs!C10*Inputs!C12))/1000 -> 0 | H21: =(50*20*Days_PM*(Inputs!C9*Inputs!C11+Inputs!C10*Inputs!C12))/1000 -> 0
A22: 30 | B22: =(2*30*Days_PM*(Inputs!C9*Inputs!C11+Inputs!C10*Inputs!C12))/1000 -> 0 | C22: =(5*30*Days_PM*(Inputs!C9*Inputs!C11+Inputs!C10*Inputs!C12))/1000 -> 0 | D22: =(8*30*Days_PM*(Inputs!C9*Inputs!C11+Inputs!C10*Inputs!C12))/1000 -> 0 | E22: =(12*30*Days_PM*(Inputs!C9*Inputs!C11+Inputs!C10*Inputs!C12))/1000 -> 0 | F22: =(20*30*Days_PM*(Inputs!C9*Inputs!C11+Inputs!C10*Inputs!C12))/1000 -> 0 | G22: =(30*30*Days_PM*(Inputs!C9*Inputs!C11+Inputs!C10*Inputs!C12))/1000 -> 0 | H22: =(50*30*Days_PM*(Inputs!C9*Inputs!C11+Inputs!C10*Inputs!C12))/1000 -> 0
A23: 50 | B23: =(2*50*Days_PM*(Inputs!C9*Inputs!C11+Inputs!C10*Inputs!C12))/1000 -> 0 | C23: =(5*50*Days_PM*(Inputs!C9*Inputs!C11+Inputs!C10*Inputs!C12))/1000 -> 0 | D23: =(8*50*Days_PM*(Inputs!C9*Inputs!C11+Inputs!C10*Inputs!C12))/1000 -> 0 | E23: =(12*50*Days_PM*(Inputs!C9*Inputs!C11+Inputs!C10*Inputs!C12))/1000 -> 0 | F23: =(20*50*Days_PM*(Inputs!C9*Inputs!C11+Inputs!C10*Inputs!C12))/1000 -> 0 | G23: =(30*50*Days_PM*(Inputs!C9*Inputs!C11+Inputs!C10*Inputs!C12))/1000 -> 0 | H23: =(50*50*Days_PM*(Inputs!C9*Inputs!C11+Inputs!C10*Inputs!C12))/1000 -> 0
A24: 80 | B24: =(2*80*Days_PM*(Inputs!C9*Inputs!C11+Inputs!C10*Inputs!C12))/1000 -> 0 | C24: =(5*80*Days_PM*(Inputs!C9*Inputs!C11+Inputs!C10*Inputs!C12))/1000 -> 0 | D24: =(8*80*Days_PM*(Inputs!C9*Inputs!C11+Inputs!C10*Inputs!C12))/1000 -> 0 | E24: =(12*80*Days_PM*(Inputs!C9*Inputs!C11+Inputs!C10*Inputs!C12))/1000 -> 0 | F24: =(20*80*Days_PM*(Inputs!C9*Inputs!C11+Inputs!C10*Inputs!C12))/1000 -> 0 | G24: =(30*80*Days_PM*(Inputs!C9*Inputs!C11+Inputs!C10*Inputs!C12))/1000 -> 0 | H24: =(50*80*Days_PM*(Inputs!C9*Inputs!C11+Inputs!C10*Inputs!C12))/1000 -> 0

Sheet Stress-Test
A1: Stress-Test Waterfall — Enterprise Tier
A3: Scenario | B3: AI cost / tenant | C3: AI GM % | D3: Above ceiling? | E3: Cost Δ vs base
A4: Baseline | B4: =(Inputs!D7*Inputs!D8*1.0*Days_PM*(Inputs!D9*1.0*Inputs!D11+Inputs!D10*1.0*Inputs!D12))/1000*(1+Inputs!D13*1.0)+Inputs!D14*1.0+Inputs!D15+Inputs!D7*Inputs!D8*1.0*Days_PM*(Inputs!D16+Inputs!D17) -> 0 | C4: =IF(Inputs!D18>0,(Inputs!D18-B4)/Inputs!D18,-1) -> 0 | D4: =IF(B4>Inputs!D18*Markup,"YES","no") -> 0 | E4: =B4-'Cost-Per-Tenant'!D11 -> 0
A5: Tokens +50% | B5: =(Inputs!D7*Inputs!D8*1.0*Days_PM*(Inputs!D9*1.5*Inputs!D11+Inputs!D10*1.5*Inputs!D12))/1000*(1+Inputs!D13*1.0)+Inputs!D14*1.0+Inputs!D15+Inputs!D7*Inputs!D8*1.0*Days_PM*(Inputs!D16+Inputs!D17) -> 0 | C5: =IF(Inputs!D18>0,(Inputs!D18-B5)/Inputs!D18,-1) -> 0 | D5: =IF(B5>Inputs!D18*Markup,"YES","no") -> 0 | E5: =B5-'Cost-Per-Tenant'!D11 -> 0
A6: Tokens +100% | B6: =(Inputs!D7*Inputs!D8*1.0*Days_PM*(Inputs!D9*2.0*Inputs!D11+Inputs!D10*2.0*Inputs!D12))/1000*(1+Inputs!D13*1.0)+Inputs!D14*1.0+Inputs!D15+Inputs!D7*Inputs!D8*1.0*Days_PM*(Inputs!D16+Inputs!D17) -> 0 | C6: =IF(Inputs!D18>0,(Inputs!D18-B6)/Inputs!D18,-1) -> 0 | D6: =IF(B6>Inputs!D18*Markup,"YES","no") -> 0 | E6: =B6-'Cost-Per-Tenant'!D11 -> 0
A7: Tokens +200% | B7: =(Inputs!D7*Inputs!D8*1.0*Days_PM*(Inputs!D9*3.0*Inputs!D11+Inputs!D10*3.0*Inputs!D12))/1000*(1+Inputs!D13*1.0)+Inputs!D14*1.0+Inputs!D15+Inputs!D7*Inputs!D8*1.0*Days_PM*(Inputs!D16+Inputs!D17) -> 0 | C7: =IF(Inputs!D18>0,(Inputs!D18-B7)/Inputs!D18,-1) -> 0 | D7: =IF(B7>Inputs!D18*Markup,"YES","no") -> 0 | E7: =B7-'Cost-Per-Tenant'!D11 -> 0
A8: Usage 2× (more prompts) | B8: =(Inputs!D7*Inputs!D8*2.0*Days_PM*(Inputs!D9*1.0*Inputs!D11+Inputs!D10*1.0*Inputs!D12))/1000*(1+Inputs!D13*1.0)+Inputs!D14*1.0+Inputs!D15+Inputs!D7*Inputs!D8*2.0*Days_PM*(Inputs!D16+Inputs!D17) -> 0 | C8: =IF(Inputs!D18>0,(Inputs!D18-B8)/Inputs!D18,-1) -> 0 | D8: =IF(B8>Inputs!D18*Markup,"YES","no") -> 0 | E8: =B8-'Cost-Per-Tenant'!D11 -> 0
A9: Retraining 2× | B9: =(Inputs!D7*Inputs!D8*1.0*Days_PM*(Inputs!D9*1.0*Inputs!D11+Inputs!D10*1.0*Inputs!D12))/1000*(1+Inputs!D13*1.0)+Inputs!D14*2.0+Inputs!D15+Inputs!D7*Inputs!D8*1.0*Days_PM*(Inputs!D16+Inputs!D17) -> 0 | C9: =IF(Inputs!D18>0,(Inputs!D18-B9)/Inputs!D18,-1) -> 0 | D9: =IF(B9>Inputs!D18*Markup,"YES","no") -> 0 | E9: =B9-'Cost-Per-Tenant'!D11 -> 0
A10: Eval 2× | B10: =(Inputs!D7*Inputs!D8*1.0*Days_PM*(Inputs!D9*1.0*Inputs!D11+Inputs!D10*1.0*Inputs!D12))/1000*(1+Inputs!D13*2.0)+Inputs!D14*1.0+Inputs!D15+Inputs!D7*Inputs!D8*1.0*Days_PM*(Inputs!D16+Inputs!D17) -> 0 | C10: =IF(Inputs!D18>0,(Inputs!D18-B10)/Inputs!D18,-1) -> 0 | D10: =IF(B10>Inputs!D18*Markup,"YES","no") -> 0 | E10: =B10-'Cost-Per-Tenant'!D11 -> 0
A11: Model deprecation (price 1.5×) | B11: =(Inputs!D7*Inputs!D8*Days_PM*(Inputs!D9*Inputs!D11*1.5+Inputs!D10*Inputs!D12*1.5))/1000*(1+Inputs!D13)+Inputs!D14+Inputs!D15+Inputs!D7*Inputs!D8*Days_PM*(Inputs!D16+Inputs!D17) -> 0 | C11: =IF(Inputs!D18>0,(Inputs!D18-B11)/Inputs!D18,-1) -> 0 | D11: =IF(B11>Inputs!D18*Markup,"YES","no") -> 0 | E11: =B11-'Cost-Per-Tenant'!D11 -> 0

Sheet Dashboard
A1: Dashboard — AI Cost-of-Tenant
A4: Free AI cost/tenant/mo | B4: ='Cost-Per-Tenant'!B11 -> 0
A5: Pro AI cost/tenant/mo | B5: ='Cost-Per-Tenant'!C11 -> 0
A6: Enterprise AI cost/tenant/mo | B6: ='Cost-Per-Tenant'!D11 -> 0
A7: Free AI GM % | B7: ='Margin-Analysis'!B7 -> 0
A8: Pro AI GM % | B8: ='Margin-Analysis'!C7 -> 0
A9: Enterprise AI GM % | B9: ='Margin-Analysis'!D7 -> 0
A10: Pro contribution margin % | B10: ='Margin-Analysis'!C11 -> 0
A11: Enterprise contribution margin % | B11: ='Margin-Analysis'!D11 -> 0
A12: Grand total AI cost / year (USD) | B12: ='Cost-Per-Tenant'!B15 -> 0
A13: Grand total AI cost / year (local) | B13: ='Cost-Per-Tenant'!B15*FX_AI -> 0

Sheet Africa-Notes
A1: Africa-Specific Adjustments & Notes
A3: FX Pass-Through | B3: USD-denominated cloud (AWS/Azure/GCP), AI APIs, and SaaS tooling sit against UGX/KES/NGN/ZAR/EGP revenue. Adjust gross-margin benchmarks 5–10pp downward vs US comps. Hold an FX rate on Inputs and stress it ±15% in the sensitivity tab.
A4: M-Pesa Payment Rail (Kenya, Tanzania) | B4: Typical fee 1.0–1.5% per transaction. STK-Push timeout failures generate involuntary churn — model 3-retry dunning over 7 days; recovery typically 30–50%. Track separately from voluntary churn.
A5: MoMo (MTN / Airtel — Uganda, Ghana, Rwanda, Nigeria) | B5: Fee band 1.5–2.0% per transaction. PIN-failure and float-shortage produce 4–6% annual involuntary churn vs <1% US card rails. Best-practice: integrate two rails (MoMo + card) and route based on tier.
A6: Card Rails (Flutterwave / Paystack / Stripe) | B6: Card fees 2.9–3.8% + fixed. Card-decline rate 8–15% on first attempt for African issuing banks. Use Account-Updater services where available.
A7: USD-Enterprise Tier | B7: Charge Enterprise customers (>$1k MRR) in USD invoiced via local entity or offshore SPV to hedge FX. Carries through to the Multi-Step P&L as a separate revenue stream. Recommended for 30–60% of total ARR by Y3.
A8: Longer Collection Cycles | B8: Enterprise/public-sector DSO in Africa: 60–120 days (vs 30–45 US). Working-capital trough is deeper. Buffer trough at 9 months of opex vs the US 6-month standard.
A9: Annual Prepayment Uptake | B9: African SaaS: 20–40% of new contracts pay annually (vs 60–80% US enterprise). Discount typically 10–15%. Model deferred revenue accordingly — do not assume US prepayment economics.
A10: Sales-Cycle Length | B10: African mid-market sales cycle: 90–180 days. Enterprise: 6–18 months including procurement / public-sector RFP loops. CAC-payback benchmarks: relax US targets by 50–100%: <18 (SMB), <24 (Mid), <36 (Ent).
A11: AI Cost Hedging | B11: LLM APIs are USD-priced. Hedge via (a) USD-priced AI premium tier, (b) per-tenant usage caps, (c) open-source model fallback (Llama-class on Bedrock/Together). The AI-cost calculator workbook models all three.
A12: DFI / Local-Bank Reporting | B12: Banks (Stanbic, Equity, KCB, Centenary) and DFIs (FMO, Norfund, Proparco, IFC) require local-currency primary view + USD parallel view. Build the model in USD here; toggle the FX row on Inputs for local presentation.
A13: Rule-of-40 Calibration | B13: Adjust to target 30 for years 1–3 of African SaaS (vs US 40). Aim for 40 by Year 4 once vertical S&M is unlocked.
A14: USD-Indexed AI Tier | B14: Because LLM pricing is USD-denominated, an FX shock instantly compresses AI margin on local-currency-priced tiers. Recommended hedge: price the Enterprise tier in USD (route via local entity or offshore SPV for invoicing) so that AI cost and price are in the same currency.
... A17: Model-Deprecation Risk | B17: Major-version model deprecations (GPT-3.5 → GPT-4 → GPT-4o → GPT-5) move pricing 30–100%. Maintain a 3-month price-tracker; the Stress-Test sheet's 'Model deprecation' row simulates a 1.5× price step.
