Workbook
Name ARPA_LP: 'Monthly-Inputs'!$B$24
Name CAC_LP: 'Monthly-Inputs'!$B$23
Name Var_Thresh: 'Monthly-Inputs'!$B$25

Sheet README
A1: SaaS Living-Plan KPI Dashboard (Monthly)
A3: Purpose | B3: 24-month rolling dashboard for SaaS. Paste monthly actuals into Monthly-Inputs; the workbook computes ARR, MRR, MoM/YoY growth, Rule of 40, NRR, GRR, Magic Number, Burn Multiple, CAC payback, LTV:CAC, Quick Ratio — auto-traffic-lighted. Variance-Tracker flags >10% deviation between plan and actual, which triggers the variance protocol per meta-living-plan-governance.
A5: Sheets in this workbook
A6: Monthly-Inputs | B6: Paste-in actuals: MRR, ARR, new logos, churned, expansion, S&M, headcount, GM. Plan vs actual columns.
A7: KPI-Dashboard | B7: Auto-calc: ARR, MRR, growth, Rule of 40, NRR, GRR, Magic Number, Burn Multiple, CAC payback, LTV:CAC, Quick Ratio. Traffic-lighted.
A8: Variance-Tracker | B8: Plan vs actual; >10% variance → REPLAN flag.
A9: Africa-Notes | B9: Reporting cadence under FX volatility; mobile-money payment-rail tracking.
A11: Owner | B11: CFO (founder pre-CFO). Reviewed monthly with CEO; quarterly with board.
A12: Update cadence | B12: Monthly close + 5 working days. Variance review same day as close.
A13: Living-plan discipline | B13: All yellow cells are user-editable inputs. White cells are formulas — do not overwrite. Refresh inputs on the cadence above. Any variance >10% versus plan triggers a re-plan loop per skills/meta-living-plan-governance.
A14: Sources / methodology | B14: meta-living-plan-governance skill; OpenView SaaS Benchmarks; saas-bankability-and-investor-readiness.
A16: Currency convention | B16: All inputs in USD. Use FX cell on Inputs sheet to display local-currency equivalents (UGX, KES, NGN, ZAR, EGP). Mobile-money (M-Pesa / MoMo) and card-rail fees enter as % of revenue.

Sheet Monthly-Inputs
A1: Monthly Inputs — Plan vs Actual
A3: Metric / Month | B3: M1 | C3: M2 | D3: M3 | E3: M4 | F3: M5 | G3: M6 | H3: M7 | I3: M8 | J3: M9 | K3: M10 | L3: M11 | M3: M12 | N3: M13 | O3: M14 | P3: M15 | Q3: M16 | R3: M17 | S3: M18 | T3: M19 | U3: M20 | V3: M21 | W3: M22 | X3: M23 | Y3: M24
A4: PLAN (set once; update at re-forecast)
A5: Plan MRR ($) | B5: 10000 | C5: 11500 | D5: 13000 | E5: 14500 | F5: 16000 | G5: 17500 | H5: 19000 | I5: 20500 | J5: 22000 | K5: 23500 | L5: 25000 | M5: 26500 | N5: 28000 | O5: 29500 | P5: 31000 | Q5: 32500 | R5: 34000 | S5: 35500 | T5: 37000 | U5: 38500 | V5: 40000 | W5: 41500 | X5: 43000 | Y5: 44500
A6: Plan New Logos | B6: 5 | C6: 5 | D6: 6 | E6: 6 | F6: 7 | G6: 8 | H6: 8 | I6: 9 | J6: 9 | K6: 10 | L6: 11 | M6: 11 | N6: 12 | O6: 12 | P6: 13 | Q6: 14 | R6: 14 | S6: 15 | T6: 15 | U6: 16 | V6: 17 | W6: 17 | X6: 18 | Y6: 18
A7: Plan Churned Logos | B7: 0 | C7: 0 | D7: 0 | E7: 0 | F7: 1 | G7: 1 | H7: 1 | I7: 1 | J7: 2 | K7: 2 | L7: 2 | M7: 2 | N7: 3 | O7: 3 | P7: 3 | Q7: 3 | R7: 4 | S7: 4 | T7: 4 | U7: 4 | V7: 5 | W7: 5 | X7: 5 | Y7: 5
A8: Plan Expansion MRR ($) | B8: 100 | C8: 200 | D8: 300 | E8: 400 | F8: 500 | G8: 600 | H8: 700 | I8: 800 | J8: 900 | K8: 1000 | L8: 1100 | M8: 1200 | N8: 1300 | O8: 1400 | P8: 1500 | Q8: 1600 | R8: 1700 | S8: 1800 | T8: 1900 | U8: 2000 | V8: 2100 | W8: 2200 | X8: 2300 | Y8: 2400
A9: Plan S&M Spend ($) | B9: 8000 | C9: 8300 | D9: 8600 | E9: 8900 | F9: 9200 | G9: 9500 | H9: 9800 | I9: 10100 | J9: 10400 | K9: 10700 | L9: 11000 | M9: 11300 | N9: 11600 | O9: 11900 | P9: 12200 | Q9: 12500 | R9: 12800 | S9: 13100 | T9: 13400 | U9: 13700 | V9: 14000 | W9: 14300 | X9: 14600 | Y9: 14900
A10: Plan Headcount | B10: 5 | C10: 5 | D10: 5 | E10: 6 | F10: 6 | G10: 6 | H10: 7 | I10: 7 | J10: 7 | K10: 8 | L10: 8 | M10: 8 | N10: 9 | O10: 9 | P10: 9 | Q10: 10 | R10: 10 | S10: 10 | T10: 11 | U10: 11 | V10: 11 | W10: 12 | X10: 12 | Y10: 12
A11: Plan Gross Margin % | B11: 0.7 | C11: 0.705 | D11: 0.71 | E11: 0.715 | F11: 0.72 | G11: 0.725 | H11: 0.73 | I11: 0.735 | J11: 0.74 | K11: 0.745 | L11: 0.75 | M11: 0.755 | N11: 0.76 | O11: 0.765 | P11: 0.77 | Q11: 0.775 | R11: 0.78 | S11: 0.785 | T11: 0.79 | U11: 0.795 | V11: 0.8 | W11: 0.8 | X11: 0.8 | Y11: 0.8
A12: Plan Cash Burn ($) | B12: 15000 | C12: 14800 | D12: 14600 | E12: 14400 | F12: 14200 | G12: 14000 | H12: 13800 | I12: 13600 | J12: 13400 | K12: 13200 | L12: 13000 | M12: 12800 | N12: 12600 | O12: 12400 | P12: 12200 | Q12: 12000 | R12: 11800 | S12: 11600 | T12: 11400 | U12: 11200 | V12: 11000 | W12: 10800 | X12: 10600 | Y12: 10400
A13: ACTUAL (paste in from billing/HR/finance systems)
A14: Actual MRR ($)
A15: Actual New Logos
A16: Actual Churned Logos
A17: Actual Expansion MRR ($)
A18: Actual S&M Spend ($)
A19: Actual Headcount
A20: Actual Gross Margin %
A21: Actual Cash Burn ($)
A22: Single-value assumptions
A23: Blended CAC ($/logo) | B23: 850
A24: ARPA ($/mo) | B24: 79
A25: Variance threshold % (trigger replan) | B25: 0.1
A26: Reporting currency | B26: UGX
A27: FX (local per USD) | B27: 3800

Sheet KPI-Dashboard
A1: KPI Dashboard — Monthly
A3: KPI / Month | B3: M1 | C3: M2 | D3: M3 | E3: M4 | F3: M5 | G3: M6 | H3: M7 | I3: M8 | J3: M9 | K3: M10 | L3: M11 | M3: M12 | N3: M13 | O3: M14 | P3: M15 | Q3: M16 | R3: M17 | S3: M18 | T3: M19 | U3: M20 | V3: M21 | W3: M22 | X3: M23 | Y3: M24
A4: MRR (actual, $) | B4: ='Monthly-Inputs'!B14 -> 0 | C4: ='Monthly-Inputs'!C14 -> 0 | D4: ='Monthly-Inputs'!D14 -> 0 | E4: ='Monthly-Inputs'!E14 -> 0 | F4: ='Monthly-Inputs'!F14 -> 0 | G4: ='Monthly-Inputs'!G14 -> 0 | H4: ='Monthly-Inputs'!H14 -> 0 | I4: ='Monthly-Inputs'!I14 -> 0 | ... Y4: ='Monthly-Inputs'!Y14 -> 0
A5: ARR (MRR×12, $) | B5: ='Monthly-Inputs'!B14*12 -> 0 | C5: ='Monthly-Inputs'!C14*12 -> 0 | D5: ='Monthly-Inputs'!D14*12 -> 0 | E5: ='Monthly-Inputs'!E14*12 -> 0 | F5: ='Monthly-Inputs'!F14*12 -> 0 | G5: ='Monthly-Inputs'!G14*12 -> 0 | H5: ='Monthly-Inputs'!H14*12 -> 0 | I5: ='Monthly-Inputs'!I14*12 -> 0 | ... Y5: ='Monthly-Inputs'!Y14*12 -> 0
A6: MoM growth % | C6: =IFERROR('Monthly-Inputs'!C14/'Monthly-Inputs'!B14-1,0) -> 0 | D6: =IFERROR('Monthly-Inputs'!D14/'Monthly-Inputs'!C14-1,0) -> 0 | E6: =IFERROR('Monthly-Inputs'!E14/'Monthly-Inputs'!D14-1,0) -> 0 | F6: =IFERROR('Monthly-Inputs'!F14/'Monthly-Inputs'!E14-1,0) -> 0 | G6: =IFERROR('Monthly-Inputs'!G14/'Monthly-Inputs'!F14-1,0) -> 0 | H6: =IFERROR('Monthly-Inputs'!H14/'Monthly-Inputs'!G14-1,0) -> 0 | I6: =IFERROR('Monthly-Inputs'!I14/'Monthly-Inputs'!H14-1,0) -> 0 | J6: =IFERROR('Monthly-Inputs'!J14/'Monthly-Inputs'!I14-1,0) -> 0 | ... Y6: =IFERROR('Monthly-Inputs'!Y14/'Monthly-Inputs'!X14-1,0) -> 0
A7: YoY growth % | N7: =IFERROR('Monthly-Inputs'!N14/'Monthly-Inputs'!B14-1,0) -> 0 | O7: =IFERROR('Monthly-Inputs'!O14/'Monthly-Inputs'!C14-1,0) -> 0 | P7: =IFERROR('Monthly-Inputs'!P14/'Monthly-Inputs'!D14-1,0) -> 0 | Q7: =IFERROR('Monthly-Inputs'!Q14/'Monthly-Inputs'!E14-1,0) -> 0 | R7: =IFERROR('Monthly-Inputs'!R14/'Monthly-Inputs'!F14-1,0) -> 0 | S7: =IFERROR('Monthly-Inputs'!S14/'Monthly-Inputs'!G14-1,0) -> 0 | T7: =IFERROR('Monthly-Inputs'!T14/'Monthly-Inputs'!H14-1,0) -> 0 | U7: =IFERROR('Monthly-Inputs'!U14/'Monthly-Inputs'!I14-1,0) -> 0 | ... Y7: =IFERROR('Monthly-Inputs'!Y14/'Monthly-Inputs'!M14-1,0) -> 0
A8: Logo Churn rate (monthly) | B8: =IFERROR('Monthly-Inputs'!B16/MAX(1,'Monthly-Inputs'!B14/ARPA_LP),0) -> 0 | C8: =IFERROR('Monthly-Inputs'!C16/MAX(1,'Monthly-Inputs'!B14/ARPA_LP),0) -> 0 | D8: =IFERROR('Monthly-Inputs'!D16/MAX(1,'Monthly-Inputs'!C14/ARPA_LP),0) -> 0 | E8: =IFERROR('Monthly-Inputs'!E16/MAX(1,'Monthly-Inputs'!D14/ARPA_LP),0) -> 0 | F8: =IFERROR('Monthly-Inputs'!F16/MAX(1,'Monthly-Inputs'!E14/ARPA_LP),0) -> 0 | G8: =IFERROR('Monthly-Inputs'!G16/MAX(1,'Monthly-Inputs'!F14/ARPA_LP),0) -> 0 | H8: =IFERROR('Monthly-Inputs'!H16/MAX(1,'Monthly-Inputs'!G14/ARPA_LP),0) -> 0 | I8: =IFERROR('Monthly-Inputs'!I16/MAX(1,'Monthly-Inputs'!H14/ARPA_LP),0) -> 0 | J8: =IFERROR('Monthly-Inputs'!J16/MAX(1,'Monthly-Inputs'!I14/ARPA_LP),0) -> 0 | ... Y8: =IFERROR('Monthly-Inputs'!Y16/MAX(1,'Monthly-Inputs'!X14/ARPA_LP),0) -> 0
A9: Expansion rate (monthly) | B9: =IFERROR('Monthly-Inputs'!B17/MAX(1,'Monthly-Inputs'!B14),0) -> 0 | C9: =IFERROR('Monthly-Inputs'!C17/MAX(1,'Monthly-Inputs'!B14),0) -> 0 | D9: =IFERROR('Monthly-Inputs'!D17/MAX(1,'Monthly-Inputs'!C14),0) -> 0 | E9: =IFERROR('Monthly-Inputs'!E17/MAX(1,'Monthly-Inputs'!D14),0) -> 0 | F9: =IFERROR('Monthly-Inputs'!F17/MAX(1,'Monthly-Inputs'!E14),0) -> 0 | G9: =IFERROR('Monthly-Inputs'!G17/MAX(1,'Monthly-Inputs'!F14),0) -> 0 | H9: =IFERROR('Monthly-Inputs'!H17/MAX(1,'Monthly-Inputs'!G14),0) -> 0 | I9: =IFERROR('Monthly-Inputs'!I17/MAX(1,'Monthly-Inputs'!H14),0) -> 0 | J9: =IFERROR('Monthly-Inputs'!J17/MAX(1,'Monthly-Inputs'!I14),0) -> 0 | ... Y9: =IFERROR('Monthly-Inputs'!Y17/MAX(1,'Monthly-Inputs'!X14),0) -> 0
A10: NRR (annual, rolling) | B10: =1+(IFERROR('Monthly-Inputs'!B17/MAX(1,'Monthly-Inputs'!B14),0)-IFERROR('Monthly-Inputs'!B16/MAX(1,'Monthly-Inputs'!B14/ARPA_LP)*ARPA_LP/MAX(1,'Monthly-Inputs'!B14),0))*12 -> 0 | C10: =1+(IFERROR('Monthly-Inputs'!C17/MAX(1,'Monthly-Inputs'!B14),0)-IFERROR('Monthly-Inputs'!C16/MAX(1,'Monthly-Inputs'!B14/ARPA_LP)*ARPA_LP/MAX(1,'Monthly-Inputs'!B14),0))*12 -> 0 | D10: =1+(IFERROR('Monthly-Inputs'!D17/MAX(1,'Monthly-Inputs'!C14),0)-IFERROR('Monthly-Inputs'!D16/MAX(1,'Monthly-Inputs'!C14/ARPA_LP)*ARPA_LP/MAX(1,'Monthly-Inputs'!C14),0))*12 -> 0 | E10: =1+(IFERROR('Monthly-Inputs'!E17/MAX(1,'Monthly-Inputs'!D14),0)-IFERROR('Monthly-Inputs'!E16/MAX(1,'Monthly-Inputs'!D14/ARPA_LP)*ARPA_LP/MAX(1,'Monthly-Inputs'!D14),0))*12 -> 0 | F10: =1+(IFERROR('Monthly-Inputs'!F17/MAX(1,'Monthly-Inputs'!E14),0)-IFERROR('Monthly-Inputs'!F16/MAX(1,'Monthly-Inputs'!E14/ARPA_LP)*ARPA_LP/MAX(1,'Monthly-Inputs'!E14),0))*12 -> 0 | G10: =1+(IFERROR('Monthly-Inputs'!G17/MAX(1,'Monthly-Inputs'!F14),0)-IFERROR('Monthly-Inputs'!G16/MAX(1,'Monthly-Inputs'!F14/ARPA_LP)*ARPA_LP/MAX(1,'Monthly-Inputs'!F14),0))*12 -> 0 | H10: =1+(IFERROR('Monthly-Inputs'!H17/MAX(1,'Monthly-Inputs'!G14),0)-IFERROR('Monthly-Inputs'!H16/MAX(1,'Monthly-Inputs'!G14/ARPA_LP)*ARPA_LP/MAX(1,'Monthly-Inputs'!G14),0))*12 -> 0 | I10: =1+(IFERROR('Monthly-Inputs'!I17/MAX(1,'Monthly-Inputs'!H14),0)-IFERROR('Monthly-Inputs'!I16/MAX(1,'Monthly-Inputs'!H14/ARPA_LP)*ARPA_LP/MAX(1,'Monthly-Inputs'!H14),0))*12 -> 0 | J10: =1+(IFERROR('Monthly-Inputs'!J17/MAX(1,'Monthly-Inputs'!I14),0)-IFERROR('Monthly-Inputs'!J16/MAX(1,'Monthly-Inputs'!I14/ARPA_LP)*ARPA_LP/MAX(1,'Monthly-Inputs'!I14),0))*12 -> 0 | ... Y10: =1+(IFERROR('Monthly-Inputs'!Y17/MAX(1,'Monthly-Inputs'!X14),0)-IFERROR('Monthly-Inputs'!Y16/MAX(1,'Monthly-Inputs'!X14/ARPA_LP)*ARPA_LP/MAX(1,'Monthly-Inputs'!X14),0))*12 -> 0
A11: GRR (annual, rolling) | B11: =MAX(0,1-IFERROR('Monthly-Inputs'!B16*ARPA_LP/MAX(1,'Monthly-Inputs'!B14),0)*12) -> 0 | C11: =MAX(0,1-IFERROR('Monthly-Inputs'!C16*ARPA_LP/MAX(1,'Monthly-Inputs'!B14),0)*12) -> 0 | D11: =MAX(0,1-IFERROR('Monthly-Inputs'!D16*ARPA_LP/MAX(1,'Monthly-Inputs'!C14),0)*12) -> 0 | E11: =MAX(0,1-IFERROR('Monthly-Inputs'!E16*ARPA_LP/MAX(1,'Monthly-Inputs'!D14),0)*12) -> 0 | F11: =MAX(0,1-IFERROR('Monthly-Inputs'!F16*ARPA_LP/MAX(1,'Monthly-Inputs'!E14),0)*12) -> 0 | G11: =MAX(0,1-IFERROR('Monthly-Inputs'!G16*ARPA_LP/MAX(1,'Monthly-Inputs'!F14),0)*12) -> 0 | H11: =MAX(0,1-IFERROR('Monthly-Inputs'!H16*ARPA_LP/MAX(1,'Monthly-Inputs'!G14),0)*12) -> 0 | I11: =MAX(0,1-IFERROR('Monthly-Inputs'!I16*ARPA_LP/MAX(1,'Monthly-Inputs'!H14),0)*12) -> 0 | J11: =MAX(0,1-IFERROR('Monthly-Inputs'!J16*ARPA_LP/MAX(1,'Monthly-Inputs'!I14),0)*12) -> 0 | ... Y11: =MAX(0,1-IFERROR('Monthly-Inputs'!Y16*ARPA_LP/MAX(1,'Monthly-Inputs'!X14),0)*12) -> 0
A12: Magic Number (3-mo trailing) | E12: =IFERROR(('Monthly-Inputs'!E14-'Monthly-Inputs'!B14)*4/('Monthly-Inputs'!D18+'Monthly-Inputs'!C18+'Monthly-Inputs'!B18),0) -> 0 | F12: =IFERROR(('Monthly-Inputs'!F14-'Monthly-Inputs'!C14)*4/('Monthly-Inputs'!E18+'Monthly-Inputs'!D18+'Monthly-Inputs'!C18),0) -> 0 | G12: =IFERROR(('Monthly-Inputs'!G14-'Monthly-Inputs'!D14)*4/('Monthly-Inputs'!F18+'Monthly-Inputs'!E18+'Monthly-Inputs'!D18),0) -> 0 | H12: =IFERROR(('Monthly-Inputs'!H14-'Monthly-Inputs'!E14)*4/('Monthly-Inputs'!G18+'Monthly-Inputs'!F18+'Monthly-Inputs'!E18),0) -> 0 | I12: =IFERROR(('Monthly-Inputs'!I14-'Monthly-Inputs'!F14)*4/('Monthly-Inputs'!H18+'Monthly-Inputs'!G18+'Monthly-Inputs'!F18),0) -> 0 | J12: =IFERROR(('Monthly-Inputs'!J14-'Monthly-Inputs'!G14)*4/('Monthly-Inputs'!I18+'Monthly-Inputs'!H18+'Monthly-Inputs'!G18),0) -> 0 | K12: =IFERROR(('Monthly-Inputs'!K14-'Monthly-Inputs'!H14)*4/('Monthly-Inputs'!J18+'Monthly-Inputs'!I18+'Monthly-Inputs'!H18),0) -> 0 | L12: =IFERROR(('Monthly-Inputs'!L14-'Monthly-Inputs'!I14)*4/('Monthly-Inputs'!K18+'Monthly-Inputs'!J18+'Monthly-Inputs'!I18),0) -> 0 | ... Y12: =IFERROR(('Monthly-Inputs'!Y14-'Monthly-Inputs'!V14)*4/('Monthly-Inputs'!X18+'Monthly-Inputs'!W18+'Monthly-Inputs'!V18),0) -> 0
A13: CAC Payback (mo) | B13: =IFERROR(CAC_LP/(ARPA_LP*'Monthly-Inputs'!B20),0) -> 0 | C13: =IFERROR(CAC_LP/(ARPA_LP*'Monthly-Inputs'!C20),0) -> 0 | D13: =IFERROR(CAC_LP/(ARPA_LP*'Monthly-Inputs'!D20),0) -> 0 | E13: =IFERROR(CAC_LP/(ARPA_LP*'Monthly-Inputs'!E20),0) -> 0 | F13: =IFERROR(CAC_LP/(ARPA_LP*'Monthly-Inputs'!F20),0) -> 0 | G13: =IFERROR(CAC_LP/(ARPA_LP*'Monthly-Inputs'!G20),0) -> 0 | H13: =IFERROR(CAC_LP/(ARPA_LP*'Monthly-Inputs'!H20),0) -> 0 | I13: =IFERROR(CAC_LP/(ARPA_LP*'Monthly-Inputs'!I20),0) -> 0 | ... Y13: =IFERROR(CAC_LP/(ARPA_LP*'Monthly-Inputs'!Y20),0) -> 0
A14: LTV:CAC | B14: =IFERROR((ARPA_LP*'Monthly-Inputs'!B20/MAX(0.001,IFERROR('Monthly-Inputs'!B16/MAX(1,'Monthly-Inputs'!B14/ARPA_LP),0)))/CAC_LP,0) -> 0 | C14: =IFERROR((ARPA_LP*'Monthly-Inputs'!C20/MAX(0.001,IFERROR('Monthly-Inputs'!C16/MAX(1,'Monthly-Inputs'!B14/ARPA_LP),0)))/CAC_LP,0) -> 0 | D14: =IFERROR((ARPA_LP*'Monthly-Inputs'!D20/MAX(0.001,IFERROR('Monthly-Inputs'!D16/MAX(1,'Monthly-Inputs'!C14/ARPA_LP),0)))/CAC_LP,0) -> 0 | E14: =IFERROR((ARPA_LP*'Monthly-Inputs'!E20/MAX(0.001,IFERROR('Monthly-Inputs'!E16/MAX(1,'Monthly-Inputs'!D14/ARPA_LP),0)))/CAC_LP,0) -> 0 | F14: =IFERROR((ARPA_LP*'Monthly-Inputs'!F20/MAX(0.001,IFERROR('Monthly-Inputs'!F16/MAX(1,'Monthly-Inputs'!E14/ARPA_LP),0)))/CAC_LP,0) -> 0 | G14: =IFERROR((ARPA_LP*'Monthly-Inputs'!G20/MAX(0.001,IFERROR('Monthly-Inputs'!G16/MAX(1,'Monthly-Inputs'!F14/ARPA_LP),0)))/CAC_LP,0) -> 0 | H14: =IFERROR((ARPA_LP*'Monthly-Inputs'!H20/MAX(0.001,IFERROR('Monthly-Inputs'!H16/MAX(1,'Monthly-Inputs'!G14/ARPA_LP),0)))/CAC_LP,0) -> 0 | I14: =IFERROR((ARPA_LP*'Monthly-Inputs'!I20/MAX(0.001,IFERROR('Monthly-Inputs'!I16/MAX(1,'Monthly-Inputs'!H14/ARPA_LP),0)))/CAC_LP,0) -> 0 | J14: =IFERROR((ARPA_LP*'Monthly-Inputs'!J20/MAX(0.001,IFERROR('Monthly-Inputs'!J16/MAX(1,'Monthly-Inputs'!I14/ARPA_LP),0)))/CAC_LP,0) -> 0 | ... Y14: =IFERROR((ARPA_LP*'Monthly-Inputs'!Y20/MAX(0.001,IFERROR('Monthly-Inputs'!Y16/MAX(1,'Monthly-Inputs'!X14/ARPA_LP),0)))/CAC_LP,0) -> 0
A15: Burn Multiple (3-mo) | E15: =IFERROR(('Monthly-Inputs'!E21+'Monthly-Inputs'!D21+'Monthly-Inputs'!C21)/MAX(1,('Monthly-Inputs'!E14-'Monthly-Inputs'!B14)*12/3),99) -> 0 | F15: =IFERROR(('Monthly-Inputs'!F21+'Monthly-Inputs'!E21+'Monthly-Inputs'!D21)/MAX(1,('Monthly-Inputs'!F14-'Monthly-Inputs'!C14)*12/3),99) -> 0 | G15: =IFERROR(('Monthly-Inputs'!G21+'Monthly-Inputs'!F21+'Monthly-Inputs'!E21)/MAX(1,('Monthly-Inputs'!G14-'Monthly-Inputs'!D14)*12/3),99) -> 0 | H15: =IFERROR(('Monthly-Inputs'!H21+'Monthly-Inputs'!G21+'Monthly-Inputs'!F21)/MAX(1,('Monthly-Inputs'!H14-'Monthly-Inputs'!E14)*12/3),99) -> 0 | I15: =IFERROR(('Monthly-Inputs'!I21+'Monthly-Inputs'!H21+'Monthly-Inputs'!G21)/MAX(1,('Monthly-Inputs'!I14-'Monthly-Inputs'!F14)*12/3),99) -> 0 | J15: =IFERROR(('Monthly-Inputs'!J21+'Monthly-Inputs'!I21+'Monthly-Inputs'!H21)/MAX(1,('Monthly-Inputs'!J14-'Monthly-Inputs'!G14)*12/3),99) -> 0 | K15: =IFERROR(('Monthly-Inputs'!K21+'Monthly-Inputs'!J21+'Monthly-Inputs'!I21)/MAX(1,('Monthly-Inputs'!K14-'Monthly-Inputs'!H14)*12/3),99) -> 0 | L15: =IFERROR(('Monthly-Inputs'!L21+'Monthly-Inputs'!K21+'Monthly-Inputs'!J21)/MAX(1,('Monthly-Inputs'!L14-'Monthly-Inputs'!I14)*12/3),99) -> 0 | ... Y15: =IFERROR(('Monthly-Inputs'!Y21+'Monthly-Inputs'!X21+'Monthly-Inputs'!W21)/MAX(1,('Monthly-Inputs'!Y14-'Monthly-Inputs'!V14)*12/3),99) -> 0
A16: Quick Ratio | B16: =IFERROR(('Monthly-Inputs'!B15*ARPA_LP+'Monthly-Inputs'!B17)/MAX(1,'Monthly-Inputs'!B16*ARPA_LP),0) -> 0 | C16: =IFERROR(('Monthly-Inputs'!C15*ARPA_LP+'Monthly-Inputs'!C17)/MAX(1,'Monthly-Inputs'!C16*ARPA_LP),0) -> 0 | D16: =IFERROR(('Monthly-Inputs'!D15*ARPA_LP+'Monthly-Inputs'!D17)/MAX(1,'Monthly-Inputs'!D16*ARPA_LP),0) -> 0 | E16: =IFERROR(('Monthly-Inputs'!E15*ARPA_LP+'Monthly-Inputs'!E17)/MAX(1,'Monthly-Inputs'!E16*ARPA_LP),0) -> 0 | F16: =IFERROR(('Monthly-Inputs'!F15*ARPA_LP+'Monthly-Inputs'!F17)/MAX(1,'Monthly-Inputs'!F16*ARPA_LP),0) -> 0 | G16: =IFERROR(('Monthly-Inputs'!G15*ARPA_LP+'Monthly-Inputs'!G17)/MAX(1,'Monthly-Inputs'!G16*ARPA_LP),0) -> 0 | H16: =IFERROR(('Monthly-Inputs'!H15*ARPA_LP+'Monthly-Inputs'!H17)/MAX(1,'Monthly-Inputs'!H16*ARPA_LP),0) -> 0 | I16: =IFERROR(('Monthly-Inputs'!I15*ARPA_LP+'Monthly-Inputs'!I17)/MAX(1,'Monthly-Inputs'!I16*ARPA_LP),0) -> 0 | ... Y16: =IFERROR(('Monthly-Inputs'!Y15*ARPA_LP+'Monthly-Inputs'!Y17)/MAX(1,'Monthly-Inputs'!Y16*ARPA_LP),0) -> 0
A17: Rule of 40 (trailing 12-mo) | N17: =IFERROR('Monthly-Inputs'!N14/MAX(1,'Monthly-Inputs'!B14)-1,0)+(('Monthly-Inputs'!N20)-(IFERROR('Monthly-Inputs'!N18+'Monthly-Inputs'!N21,0))/MAX(1,'Monthly-Inputs'!N14)) -> 0 | O17: =IFERROR('Monthly-Inputs'!O14/MAX(1,'Monthly-Inputs'!C14)-1,0)+(('Monthly-Inputs'!O20)-(IFERROR('Monthly-Inputs'!O18+'Monthly-Inputs'!O21,0))/MAX(1,'Monthly-Inputs'!O14)) -> 0 | P17: =IFERROR('Monthly-Inputs'!P14/MAX(1,'Monthly-Inputs'!D14)-1,0)+(('Monthly-Inputs'!P20)-(IFERROR('Monthly-Inputs'!P18+'Monthly-Inputs'!P21,0))/MAX(1,'Monthly-Inputs'!P14)) -> 0 | Q17: =IFERROR('Monthly-Inputs'!Q14/MAX(1,'Monthly-Inputs'!E14)-1,0)+(('Monthly-Inputs'!Q20)-(IFERROR('Monthly-Inputs'!Q18+'Monthly-Inputs'!Q21,0))/MAX(1,'Monthly-Inputs'!Q14)) -> 0 | R17: =IFERROR('Monthly-Inputs'!R14/MAX(1,'Monthly-Inputs'!F14)-1,0)+(('Monthly-Inputs'!R20)-(IFERROR('Monthly-Inputs'!R18+'Monthly-Inputs'!R21,0))/MAX(1,'Monthly-Inputs'!R14)) -> 0 | S17: =IFERROR('Monthly-Inputs'!S14/MAX(1,'Monthly-Inputs'!G14)-1,0)+(('Monthly-Inputs'!S20)-(IFERROR('Monthly-Inputs'!S18+'Monthly-Inputs'!S21,0))/MAX(1,'Monthly-Inputs'!S14)) -> 0 | T17: =IFERROR('Monthly-Inputs'!T14/MAX(1,'Monthly-Inputs'!H14)-1,0)+(('Monthly-Inputs'!T20)-(IFERROR('Monthly-Inputs'!T18+'Monthly-Inputs'!T21,0))/MAX(1,'Monthly-Inputs'!T14)) -> 0 | U17: =IFERROR('Monthly-Inputs'!U14/MAX(1,'Monthly-Inputs'!I14)-1,0)+(('Monthly-Inputs'!U20)-(IFERROR('Monthly-Inputs'!U18+'Monthly-Inputs'!U21,0))/MAX(1,'Monthly-Inputs'!U14)) -> 0 | ... Y17: =IFERROR('Monthly-Inputs'!Y14/MAX(1,'Monthly-Inputs'!M14)-1,0)+(('Monthly-Inputs'!Y20)-(IFERROR('Monthly-Inputs'!Y18+'Monthly-Inputs'!Y21,0))/MAX(1,'Monthly-Inputs'!Y14)) -> 0

Sheet Variance-Tracker
A1: Variance Tracker — Plan vs Actual (>10% triggers REPLAN)
A3: Metric / Month | B3: M1 | C3: M2 | D3: M3 | E3: M4 | F3: M5 | G3: M6 | H3: M7 | I3: M8 | J3: M9 | K3: M10 | L3: M11 | M3: M12 | N3: M13 | O3: M14 | P3: M15 | Q3: M16 | R3: M17 | S3: M18 | T3: M19 | U3: M20 | V3: M21 | W3: M22 | X3: M23 | Y3: M24
A4: MRR variance % | B4: =IFERROR(('Monthly-Inputs'!B14-'Monthly-Inputs'!B5)/MAX(1,'Monthly-Inputs'!B5),0) -> 0 | C4: =IFERROR(('Monthly-Inputs'!C14-'Monthly-Inputs'!C5)/MAX(1,'Monthly-Inputs'!C5),0) -> 0 | D4: =IFERROR(('Monthly-Inputs'!D14-'Monthly-Inputs'!D5)/MAX(1,'Monthly-Inputs'!D5),0) -> 0 | E4: =IFERROR(('Monthly-Inputs'!E14-'Monthly-Inputs'!E5)/MAX(1,'Monthly-Inputs'!E5),0) -> 0 | F4: =IFERROR(('Monthly-Inputs'!F14-'Monthly-Inputs'!F5)/MAX(1,'Monthly-Inputs'!F5),0) -> 0 | G4: =IFERROR(('Monthly-Inputs'!G14-'Monthly-Inputs'!G5)/MAX(1,'Monthly-Inputs'!G5),0) -> 0 | H4: =IFERROR(('Monthly-Inputs'!H14-'Monthly-Inputs'!H5)/MAX(1,'Monthly-Inputs'!H5),0) -> 0 | I4: =IFERROR(('Monthly-Inputs'!I14-'Monthly-Inputs'!I5)/MAX(1,'Monthly-Inputs'!I5),0) -> 0 | ... Y4: =IFERROR(('Monthly-Inputs'!Y14-'Monthly-Inputs'!Y5)/MAX(1,'Monthly-Inputs'!Y5),0) -> 0
A5: New Logos variance % | B5: =IFERROR(('Monthly-Inputs'!B15-'Monthly-Inputs'!B6)/MAX(1,'Monthly-Inputs'!B6),0) -> 0 | C5: =IFERROR(('Monthly-Inputs'!C15-'Monthly-Inputs'!C6)/MAX(1,'Monthly-Inputs'!C6),0) -> 0 | D5: =IFERROR(('Monthly-Inputs'!D15-'Monthly-Inputs'!D6)/MAX(1,'Monthly-Inputs'!D6),0) -> 0 | E5: =IFERROR(('Monthly-Inputs'!E15-'Monthly-Inputs'!E6)/MAX(1,'Monthly-Inputs'!E6),0) -> 0 | F5: =IFERROR(('Monthly-Inputs'!F15-'Monthly-Inputs'!F6)/MAX(1,'Monthly-Inputs'!F6),0) -> 0 | G5: =IFERROR(('Monthly-Inputs'!G15-'Monthly-Inputs'!G6)/MAX(1,'Monthly-Inputs'!G6),0) -> 0 | H5: =IFERROR(('Monthly-Inputs'!H15-'Monthly-Inputs'!H6)/MAX(1,'Monthly-Inputs'!H6),0) -> 0 | I5: =IFERROR(('Monthly-Inputs'!I15-'Monthly-Inputs'!I6)/MAX(1,'Monthly-Inputs'!I6),0) -> 0 | ... Y5: =IFERROR(('Monthly-Inputs'!Y15-'Monthly-Inputs'!Y6)/MAX(1,'Monthly-Inputs'!Y6),0) -> 0
A6: S&M Spend variance % | B6: =IFERROR(('Monthly-Inputs'!B18-'Monthly-Inputs'!B9)/MAX(1,'Monthly-Inputs'!B9),0) -> 0 | C6: =IFERROR(('Monthly-Inputs'!C18-'Monthly-Inputs'!C9)/MAX(1,'Monthly-Inputs'!C9),0) -> 0 | D6: =IFERROR(('Monthly-Inputs'!D18-'Monthly-Inputs'!D9)/MAX(1,'Monthly-Inputs'!D9),0) -> 0 | E6: =IFERROR(('Monthly-Inputs'!E18-'Monthly-Inputs'!E9)/MAX(1,'Monthly-Inputs'!E9),0) -> 0 | F6: =IFERROR(('Monthly-Inputs'!F18-'Monthly-Inputs'!F9)/MAX(1,'Monthly-Inputs'!F9),0) -> 0 | G6: =IFERROR(('Monthly-Inputs'!G18-'Monthly-Inputs'!G9)/MAX(1,'Monthly-Inputs'!G9),0) -> 0 | H6: =IFERROR(('Monthly-Inputs'!H18-'Monthly-Inputs'!H9)/MAX(1,'Monthly-Inputs'!H9),0) -> 0 | I6: =IFERROR(('Monthly-Inputs'!I18-'Monthly-Inputs'!I9)/MAX(1,'Monthly-Inputs'!I9),0) -> 0 | ... Y6: =IFERROR(('Monthly-Inputs'!Y18-'Monthly-Inputs'!Y9)/MAX(1,'Monthly-Inputs'!Y9),0) -> 0
A7: Headcount variance % | B7: =IFERROR(('Monthly-Inputs'!B19-'Monthly-Inputs'!B10)/MAX(1,'Monthly-Inputs'!B10),0) -> 0 | C7: =IFERROR(('Monthly-Inputs'!C19-'Monthly-Inputs'!C10)/MAX(1,'Monthly-Inputs'!C10),0) -> 0 | D7: =IFERROR(('Monthly-Inputs'!D19-'Monthly-Inputs'!D10)/MAX(1,'Monthly-Inputs'!D10),0) -> 0 | E7: =IFERROR(('Monthly-Inputs'!E19-'Monthly-Inputs'!E10)/MAX(1,'Monthly-Inputs'!E10),0) -> 0 | F7: =IFERROR(('Monthly-Inputs'!F19-'Monthly-Inputs'!F10)/MAX(1,'Monthly-Inputs'!F10),0) -> 0 | G7: =IFERROR(('Monthly-Inputs'!G19-'Monthly-Inputs'!G10)/MAX(1,'Monthly-Inputs'!G10),0) -> 0 | H7: =IFERROR(('Monthly-Inputs'!H19-'Monthly-Inputs'!H10)/MAX(1,'Monthly-Inputs'!H10),0) -> 0 | I7: =IFERROR(('Monthly-Inputs'!I19-'Monthly-Inputs'!I10)/MAX(1,'Monthly-Inputs'!I10),0) -> 0 | ... Y7: =IFERROR(('Monthly-Inputs'!Y19-'Monthly-Inputs'!Y10)/MAX(1,'Monthly-Inputs'!Y10),0) -> 0
A8: Gross Margin variance pp | B8: =IFERROR('Monthly-Inputs'!B20-'Monthly-Inputs'!B11,0) -> 0 | C8: =IFERROR('Monthly-Inputs'!C20-'Monthly-Inputs'!C11,0) -> 0 | D8: =IFERROR('Monthly-Inputs'!D20-'Monthly-Inputs'!D11,0) -> 0 | E8: =IFERROR('Monthly-Inputs'!E20-'Monthly-Inputs'!E11,0) -> 0 | F8: =IFERROR('Monthly-Inputs'!F20-'Monthly-Inputs'!F11,0) -> 0 | G8: =IFERROR('Monthly-Inputs'!G20-'Monthly-Inputs'!G11,0) -> 0 | H8: =IFERROR('Monthly-Inputs'!H20-'Monthly-Inputs'!H11,0) -> 0 | I8: =IFERROR('Monthly-Inputs'!I20-'Monthly-Inputs'!I11,0) -> 0 | ... Y8: =IFERROR('Monthly-Inputs'!Y20-'Monthly-Inputs'!Y11,0) -> 0
A9: Cash Burn variance % | B9: =IFERROR(('Monthly-Inputs'!B21-'Monthly-Inputs'!B12)/MAX(1,'Monthly-Inputs'!B12),0) -> 0 | C9: =IFERROR(('Monthly-Inputs'!C21-'Monthly-Inputs'!C12)/MAX(1,'Monthly-Inputs'!C12),0) -> 0 | D9: =IFERROR(('Monthly-Inputs'!D21-'Monthly-Inputs'!D12)/MAX(1,'Monthly-Inputs'!D12),0) -> 0 | E9: =IFERROR(('Monthly-Inputs'!E21-'Monthly-Inputs'!E12)/MAX(1,'Monthly-Inputs'!E12),0) -> 0 | F9: =IFERROR(('Monthly-Inputs'!F21-'Monthly-Inputs'!F12)/MAX(1,'Monthly-Inputs'!F12),0) -> 0 | G9: =IFERROR(('Monthly-Inputs'!G21-'Monthly-Inputs'!G12)/MAX(1,'Monthly-Inputs'!G12),0) -> 0 | H9: =IFERROR(('Monthly-Inputs'!H21-'Monthly-Inputs'!H12)/MAX(1,'Monthly-Inputs'!H12),0) -> 0 | I9: =IFERROR(('Monthly-Inputs'!I21-'Monthly-Inputs'!I12)/MAX(1,'Monthly-Inputs'!I12),0) -> 0 | ... Y9: =IFERROR(('Monthly-Inputs'!Y21-'Monthly-Inputs'!Y12)/MAX(1,'Monthly-Inputs'!Y12),0) -> 0
A11: REPLAN FLAG (any metric >|threshold|) | B11: =IF(MAX(ABS(B4),ABS(B5),ABS(B6),ABS(B7),ABS(B8),ABS(B9))>Var_Thresh,"REPLAN","OK") -> 0 | C11: =IF(MAX(ABS(C4),ABS(C5),ABS(C6),ABS(C7),ABS(C8),ABS(C9))>Var_Thresh,"REPLAN","OK") -> 0 | D11: =IF(MAX(ABS(D4),ABS(D5),ABS(D6),ABS(D7),ABS(D8),ABS(D9))>Var_Thresh,"REPLAN","OK") -> 0 | E11: =IF(MAX(ABS(E4),ABS(E5),ABS(E6),ABS(E7),ABS(E8),ABS(E9))>Var_Thresh,"REPLAN","OK") -> 0 | F11: =IF(MAX(ABS(F4),ABS(F5),ABS(F6),ABS(F7),ABS(F8),ABS(F9))>Var_Thresh,"REPLAN","OK") -> 0 | G11: =IF(MAX(ABS(G4),ABS(G5),ABS(G6),ABS(G7),ABS(G8),ABS(G9))>Var_Thresh,"REPLAN","OK") -> 0 | H11: =IF(MAX(ABS(H4),ABS(H5),ABS(H6),ABS(H7),ABS(H8),ABS(H9))>Var_Thresh,"REPLAN","OK") -> 0 | I11: =IF(MAX(ABS(I4),ABS(I5),ABS(I6),ABS(I7),ABS(I8),ABS(I9))>Var_Thresh,"REPLAN","OK") -> 0 | ... Y11: =IF(MAX(ABS(Y4),ABS(Y5),ABS(Y6),ABS(Y7),ABS(Y8),ABS(Y9))>Var_Thresh,"REPLAN","OK") -> 0

Sheet Africa-Notes
A1: Africa-Specific Adjustments & Notes
A3: FX Pass-Through | B3: USD-denominated cloud (AWS/Azure/GCP), AI APIs, and SaaS tooling sit against UGX/KES/NGN/ZAR/EGP revenue. Adjust gross-margin benchmarks 5–10pp downward vs US comps. Hold an FX rate on Inputs and stress it ±15% in the sensitivity tab.
A4: M-Pesa Payment Rail (Kenya, Tanzania) | B4: Typical fee 1.0–1.5% per transaction. STK-Push timeout failures generate involuntary churn — model 3-retry dunning over 7 days; recovery typically 30–50%. Track separately from voluntary churn.
A5: MoMo (MTN / Airtel — Uganda, Ghana, Rwanda, Nigeria) | B5: Fee band 1.5–2.0% per transaction. PIN-failure and float-shortage produce 4–6% annual involuntary churn vs <1% US card rails. Best-practice: integrate two rails (MoMo + card) and route based on tier.
A6: Card Rails (Flutterwave / Paystack / Stripe) | B6: Card fees 2.9–3.8% + fixed. Card-decline rate 8–15% on first attempt for African issuing banks. Use Account-Updater services where available.
A7: USD-Enterprise Tier | B7: Charge Enterprise customers (>$1k MRR) in USD invoiced via local entity or offshore SPV to hedge FX. Carries through to the Multi-Step P&L as a separate revenue stream. Recommended for 30–60% of total ARR by Y3.
A8: Longer Collection Cycles | B8: Enterprise/public-sector DSO in Africa: 60–120 days (vs 30–45 US). Working-capital trough is deeper. Buffer trough at 9 months of opex vs the US 6-month standard.
A9: Annual Prepayment Uptake | B9: African SaaS: 20–40% of new contracts pay annually (vs 60–80% US enterprise). Discount typically 10–15%. Model deferred revenue accordingly — do not assume US prepayment economics.
A10: Sales-Cycle Length | B10: African mid-market sales cycle: 90–180 days. Enterprise: 6–18 months including procurement / public-sector RFP loops. CAC-payback benchmarks: relax US targets by 50–100%: <18 (SMB), <24 (Mid), <36 (Ent).
A11: AI Cost Hedging | B11: LLM APIs are USD-priced. Hedge via (a) USD-priced AI premium tier, (b) per-tenant usage caps, (c) open-source model fallback (Llama-class on Bedrock/Together). The AI-cost calculator workbook models all three.
A12: DFI / Local-Bank Reporting | B12: Banks (Stanbic, Equity, KCB, Centenary) and DFIs (FMO, Norfund, Proparco, IFC) require local-currency primary view + USD parallel view. Build the model in USD here; toggle the FX row on Inputs for local presentation.
A13: Rule-of-40 Calibration | B13: Adjust to target 30 for years 1–3 of African SaaS (vs US 40). Aim for 40 by Year 4 once vertical S&M is unlocked.
A14: Monthly Close Cadence under FX Volatility | B14: Re-cut MRR in USD and reporting-currency simultaneously each month. A 5–8% FX move can produce a >10% variance against plan even when underlying logo/usage trends are on plan. Variance-Tracker exposes this — flag FX-driven variance separately from operating variance.
A15: Payment-Rail Reconciliation | B15: Reconcile MRR collected via M-Pesa, MoMo, and card separately each month. Track payment-failure (involuntary churn) trend per rail — a rail-specific spike (e.g., MoMo float-shortage period) is operationally different from voluntary churn and requires a different fix.
